ocean4dvarnet/__init__.py
ocean4dvarnet/data.py
ocean4dvarnet/evaluate.py
ocean4dvarnet/models.py
ocean4dvarnet/plot.py
ocean4dvarnet/process.py
ocean4dvarnet/train.py
ocean4dvarnet/utils.py
ocean4dvarnet-1.0.5.dist-info/licenses/LICENSE
ocean4dvarnet-1.0.5.dist-info/METADATA
ocean4dvarnet-1.0.5.dist-info/WHEEL
ocean4dvarnet-1.0.5.dist-info/top_level.txt
ocean4dvarnet-1.0.5.dist-info/RECORD
