Metadata-Version: 2.4
Name: ocean4dvarnet
Version: 1.0.5
Summary: A computer program whose purpose is to apply deep learning schemes to dynamical systems and ocean remote sensing data.
Author-email: Ronan Fablet <ronan.fablet@imt-atlantique.fr>, Quentin Febvre <quentin.febvre@ifremer.fr>, Pierre Haslee <author@example.com>, DanieL Zhu <daniel.zhu@imt-atlantique.fr>, Hugo Georgenthum <hugo.georgenthum@imt-atlantique.fr>, Braux Emmanuel <emmanuel.braux@imt-atlantique.fr>
Project-URL: Homepage, https://github.io//CIA-Oceanix/ocean4dvarnet/
Project-URL: Documentation, https://CIA-Oceanix.github.io/ocean4dvarnet/
Project-URL: Repository, https://github.com/CIA-Oceanix/ocean4dvarnet
Project-URL: Issues, https://github.com//CIA-Oceanix/ocean4dvarnet/issues
Classifier: Programming Language :: Python :: 3
Classifier: Operating System :: OS Independent
Requires-Python: ~=3.10
License-File: LICENSE
Requires-Dist: xarray==2025.1.2
Requires-Dist: netcdf4<2.0.0,>=1.7.2
Requires-Dist: numpy==1.26.4
Requires-Dist: pandas
Requires-Dist: pytorch-lightning==2.3.3
Provides-Extra: dev
Requires-Dist: pylint; extra == "dev"
Requires-Dist: pytest; extra == "dev"
Requires-Dist: pytest-cov; extra == "dev"
Requires-Dist: tox; extra == "dev"
Requires-Dist: tomli; extra == "dev"
Requires-Dist: tomli-w; extra == "dev"
Requires-Dist: flake8; extra == "dev"
Requires-Dist: flake8-pyproject; extra == "dev"
Requires-Dist: black; extra == "dev"
Requires-Dist: isort; extra == "dev"
Requires-Dist: mypy; extra == "dev"
Requires-Dist: bandit; extra == "dev"
Requires-Dist: safety; extra == "dev"
Requires-Dist: ruff; extra == "dev"
Provides-Extra: doc
Requires-Dist: mkdocs; extra == "doc"
Requires-Dist: mkdocs-material; extra == "doc"
Requires-Dist: mkdocstrings; extra == "doc"
Requires-Dist: mkdocstrings-python; extra == "doc"
Provides-Extra: pypi
Requires-Dist: build; extra == "pypi"
Requires-Dist: twine; extra == "pypi"
Requires-Dist: tomli; extra == "pypi"
Requires-Dist: tomli-w; extra == "pypi"
Dynamic: license-file
